tanzania-locations/__init__.py
tanzania-locations/data.py
tanzania-locations/django.py
tanzania-locations/utils.py
tanzania_locations/__init__.py
tanzania_locations/data.py
tanzania_locations/django.py
tanzania_locations/utils.py
tanzania_locations-1.5.0.dist-info/METADATA
tanzania_locations-1.5.0.dist-info/WHEEL
tanzania_locations-1.5.0.dist-info/entry_points.txt
tanzania_locations-1.5.0.dist-info/top_level.txt
tanzania_locations-1.5.0.dist-info/RECORD
