Metadata-Version: 2.1
Name: tanzania-locations
Version: 1.5.0
Summary: Tanzania regions and districts package
Home-page: https://github.com/yourusername/tanzania-locations
Author: Cornel Mtavangu
Author-email: mtavangucornel@gmail.com
License: MIT
Classifier: Programming Language :: Python :: 3
Classifier: License :: OSI Approved :: MIT License
Classifier: Operating System :: OS Independent
Requires-Python: >=3.7
